pyopdll/__init__.py
pyopdll/op.py
pyopdll/op_x64.dll
pyopdll/op_x86.dll
pyopdll-0.0.1.dist-info/LICENSE
pyopdll-0.0.1.dist-info/METADATA
pyopdll-0.0.1.dist-info/WHEEL
pyopdll-0.0.1.dist-info/top_level.txt
pyopdll-0.0.1.dist-info/RECORD
