Metadata-Version: 2.1
Name: pyopdll
Version: 0.0.1
Summary: OP插件的Python接口
Home-page: https://github.com/Gaoyongxian666/pyopdll
Author: Gaoyongxian666
Author-email: g1695698547@163.com
License: UNKNOWN
Project-URL: Bug Reports, https://github.com/Gaoyongxian666/pyopdll
Project-URL: Source, https://github.com/Gaoyongxian666/pyopdll
Platform: UNKNOWN
Classifier: Programming Language :: Python :: 3
Classifier: License :: OSI Approved :: MIT License
Classifier: Operating System :: OS Independent
Requires-Dist: pywin32
